preferences_utils/__init__.py
preferences_utils/admin.py
preferences_utils/apps.py
preferences_utils/context_processors.py
preferences_utils/models.py
preferences_utils/migrations/__init__.py
preferences_utils/templates/admin/preferences_utils/change_form.html
preferences_utils/templatetags/preferences_utils.py
django_preferences_utils-0.1.0.dist-info/AUTHORS.rst
django_preferences_utils-0.1.0.dist-info/LICENSE
django_preferences_utils-0.1.0.dist-info/METADATA
django_preferences_utils-0.1.0.dist-info/WHEEL
django_preferences_utils-0.1.0.dist-info/top_level.txt
django_preferences_utils-0.1.0.dist-info/RECORD
