Metadata-Version: 2.1
Name: django-preferences-utils
Version: 0.1.0
Summary: All you need for your django project settings
Home-page: https://github.com/otto-torino/django-preferences-utils
Author: abidibo
Author-email: abidibo@gmail.com
License: MIT
Project-URL: Source, https://github.com/otto-torino/django-preferences-utils
Project-URL: Tracker, https://github.com/otto-torino/django-preferences-utils/issues
Keywords: django-preferences-utils
Classifier: Development Status :: 5 - Production/Stable
Classifier: Framework :: Django :: 4.2
Classifier: Framework :: Django :: 5.0
Classifier: Framework :: Django :: 5.1
Classifier: Intended Audience :: Developers
Classifier: License :: OSI Approved :: MIT License
Classifier: Natural Language :: English
Classifier: Programming Language :: Python :: 3.8
Classifier: Programming Language :: Python :: 3.9
Classifier: Programming Language :: Python :: 3.10
Classifier: Programming Language :: Python :: 3.11
Classifier: Programming Language :: Python :: 3.12
License-File: LICENSE
License-File: AUTHORS.rst
